leaseweb/__init__.py
leaseweb/api.py
leaseweb-0.1.1.dist-info/DESCRIPTION.rst
leaseweb-0.1.1.dist-info/METADATA
leaseweb-0.1.1.dist-info/RECORD
leaseweb-0.1.1.dist-info/WHEEL
leaseweb-0.1.1.dist-info/entry_points.txt
leaseweb-0.1.1.dist-info/metadata.json
leaseweb-0.1.1.dist-info/top_level.txt
leaseweb-0.1.1.dist-info/zip-safe
