Metadata-Version: 2.0
Name: leaseweb
Version: 0.1.1
Summary: Python wrapper for the Leaseweb Virtual Servers API
Home-page: UNKNOWN
Author: Iwan in 't Groen
Author-email: iwanintgroen@gmail.com
License: MIT
Platform: UNKNOWN
Classifier: Programming Language :: Python :: 3.6
Requires-Dist: requests
